setup.py
Devil/Devil.cpython-311.so
Devil/Devil.py
Devil/__init__.py
Devil/setup.py
Jython_File.egg-info/PKG-INFO
Jython_File.egg-info/SOURCES.txt
Jython_File.egg-info/dependency_links.txt
Jython_File.egg-info/top_level.txt